topo/__init__.py
topo/pipes.py
topo/plot.py
topo/single_cell.py
topo/topograph.py
topo/version.py
topo/base/__init__.py
topo/base/ann.py
topo/base/dists.py
topo/base/sparse.py
topo/eval/__init__.py
topo/eval/global_scores.py
topo/eval/local_scores.py
topo/eval/rmetric.py
topo/layouts/__init__.py
topo/layouts/graph_utils.py
topo/layouts/isomap.py
topo/layouts/map.py
topo/layouts/projector.py
topo/spectral/__init__.py
topo/spectral/_spectral.py
topo/spectral/eigen.py
topo/spectral/locally.py
topo/spectral/umap_layouts.py
topo/tpgraph/__init__.py
topo/tpgraph/cknn.py
topo/tpgraph/fuzzy.py
topo/tpgraph/intrinsic_dim.py
topo/tpgraph/kernels.py
topo/tpgraph/procrustes.py
topo/utils/__init__.py
topo/utils/_utils.py
topo/utils/umap_utils.py
topometry-0.2.1.1.dist-info/LICENSE
topometry-0.2.1.1.dist-info/METADATA
topometry-0.2.1.1.dist-info/WHEEL
topometry-0.2.1.1.dist-info/top_level.txt
topometry-0.2.1.1.dist-info/RECORD
