Metadata-Version: 2.1
Name: topometry
Version: 0.2.1.1
Summary: A comprehensive dimensional reduction framework to recover latent information from data.
Home-page: https://github.com/davisidarta/topometry
Author: Davi Sidarta-Oliveira
Author-email: davi.oliveira@dpag.ox.ac.uk
License: UNKNOWN
Project-URL: Bug Tracker, https://github.com/davisidarta/topometry/issues
Platform: UNKNOWN
Classifier: Programming Language :: Python :: 3
Classifier: License :: OSI Approved :: MIT License
Classifier: Operating System :: OS Independent
Requires-Python: >=3.6
License-File: LICENSE
Requires-Dist: matplotlib
Requires-Dist: numba
Requires-Dist: numpy
Requires-Dist: pandas
Requires-Dist: scikit-learn
Requires-Dist: scipy
Requires-Dist: setuptools
